CHANGELOG.txt
LICENSE.txt
MANIFEST.in
README.rst
setup.py
DamPch/__init__.py
DamPch.egg-info/PKG-INFO
DamPch.egg-info/SOURCES.txt
DamPch.egg-info/dependency_links.txt
DamPch.egg-info/requires.txt
DamPch.egg-info/top_level.txt