Metadata-Version: 2.1
Name: DamPch
Version: 0.0.6
Summary: A placeholder and string binding models package
Home-page: UNKNOWN
Author: Zin-Lin-Htun
Author-email: zinlinhtun34@gmail.com
License: UNKNOWN
Keywords: tkinter placeholders
Platform: UNKNOWN
Classifier: Programming Language :: Python :: 3
Classifier: License :: OSI Approved :: MIT License
Classifier: Operating System :: OS Independent
Requires-Python: >=3.8
